fly2p/__init__.py
fly2p/preproc/__init__.py
fly2p/preproc/imgPreproc.py
fly2p/preproc/microManagerUtils.py
fly2p/preproc/scanImageUtils.py
fly2p/viz/__init__.py
fly2p/viz/viz.py
fly2p-0.2.2.dist-info/METADATA
fly2p-0.2.2.dist-info/WHEEL
fly2p-0.2.2.dist-info/RECORD
