Metadata-Version: 2.1
Name: fly2p
Version: 0.2.2
Summary: Tools for analyzing 2p (calcium) imaging data collected in flies (or other insects).
License: MIT
Author: hjmh
Author-email: hjmhaberkern@gmail.com
Requires-Python: >=3.8,<4.0
Classifier: License :: OSI Approved :: MIT License
Classifier: Programming Language :: Python :: 3
Classifier: Programming Language :: Python :: 3.8
Classifier: Programming Language :: Python :: 3.9
Classifier: Programming Language :: Python :: 3.10
Classifier: Programming Language :: Python :: 3.11
Classifier: Programming Language :: Python :: 3.12
Requires-Dist: Shapely (>=1.7.1,<2.0.0)
Requires-Dist: anywidget (==0.4.2)
Requires-Dist: h5py (>=3.1.0,<4.0.0)
Requires-Dist: imjoy (>=0.11.20,<0.12.0)
Requires-Dist: ipywidgets (==8.1.1)
Requires-Dist: matplotlib (>=3.3.3,<4.0.0)
Requires-Dist: napari (>=0.4.3,<0.5.0)
Requires-Dist: pandas (>=1.2.1,<2.0.0)
Requires-Dist: pyyaml (>=6.0.1)
Requires-Dist: scanimage-tiff-reader (>=1.4.1)
Requires-Dist: scikit-image (>=0.19.3,<0.20.0)
Requires-Dist: scikit-learn (>=1.1.3,<2.0.0)
Requires-Dist: scipy (>=1.6.0,<2.0.0)
Requires-Dist: seaborn (==0.12.2)
Requires-Dist: tiffile (>=2018.10.18,<2019.0.0)
Requires-Dist: topas2numpy (>=0.2.0,<0.3.0)
Requires-Dist: typing-extensions (==4.8.0)
Requires-Dist: vispy (>=0.13.0)
Requires-Dist: vizarr (>=0.0.1,<0.0.2)
Requires-Dist: xarray (>=0.16.2,<0.17.0)
Requires-Dist: xpublish (==0.3.0)
Requires-Dist: zarr (>=2.16.1,<3.0.0)
